positivo_appium_extensions/__init__.py
positivo_appium_extensions/keywords/ChangeTheme.py
positivo_appium_extensions/keywords/ClickElements.py
positivo_appium_extensions/keywords/CompareScreenshots.py
positivo_appium_extensions/keywords/NetworkStatus.py
positivo_appium_extensions/keywords/PerformLongPress.py
positivo_appium_extensions/keywords/PerformPinch.py
positivo_appium_extensions/keywords/PerformZoom.py
positivo_appium_extensions/keywords/ScrollInside.py
positivo_appium_extensions/keywords/ScrollToElement.py
positivo_appium_extensions/keywords/SwipeElement.py
positivo_appium_extensions/keywords/TapAtPercentage.py
positivo_appium_extensions/keywords/TapElementAtCoordinates.py
positivo_appium_extensions/keywords/TerminateApplicationExtension.py
positivo_appium_extensions/keywords/VisibleElements.py
positivo_appium_extensions/keywords/WaitMultipleElements.py
positivo_appium_extensions/keywords/_BaseKeyword.py
positivo_appium_extensions/keywords/__init__.py
positivo_appium_extensions/keywords/gestures.py
positivo_appium_extensions/keywords/utils.py
positivo_appium_extensions/keywords/validators.py
positivo_appium_extensions-1.2.1.dist-info/licenses/LICENSE
positivo_appium_extensions-1.2.1.dist-info/METADATA
positivo_appium_extensions-1.2.1.dist-info/WHEEL
positivo_appium_extensions-1.2.1.dist-info/top_level.txt
positivo_appium_extensions-1.2.1.dist-info/RECORD
