Metadata-Version: 2.4
Name: positivo-appium-extensions
Version: 1.2.1
Summary: Additional keywords for Robot Framework's AppiumLibrary. Developed within the Technology Residency Program executed by CEPEDI, coordinated by SOFTEX, and supported by MCTI, with the participation of Positivo Tecnologia as the partner company that proposed the development challenge.
Author: Equipe de QA - CEPEDI / RESTIC36
Maintainer-email: Diogo Dorea <diogodorea@gmail.com>, Eduardo Takeshi <wattksh@gmail.com>, Fabio Nilo <fabionilosoares@gmail.com>, Gabriel Cerqueira <gcacarvalho.cic@uesc.br>, Geovane Glória <geovaneglorialima@gmail.com>, Henio Pedro <henioslv@gmail.com>, Marya Fernandes <marya_matos@hotmail.com>, Thalles Cardoso <thallescard@gmail.com>, Lucas de Eiroz Rodrigues <lucas.de.eiroz@gmail.com>
License-Expression: Apache-2.0
Project-URL: Homepage, https://github.com/lucasdeeiroz/positivo-appium-extensions
Project-URL: Documentation, https://github.com/lucasdeeiroz/positivo-appium-extensions/blob/develop/README.md
Project-URL: Changelog, https://github.com/lucasdeeiroz/positivo-appium-extensions/blob/develop/docs/CHANGELOG.md
Keywords: robotframework,appium,mobile,automation,android,testing
Classifier: Development Status :: 4 - Beta
Classifier: Intended Audience :: Developers
Classifier: Operating System :: OS Independent
Classifier: Programming Language :: Python :: 3
Classifier: Programming Language :: Python :: 3.9
Classifier: Programming Language :: Python :: 3.12
Classifier: Framework :: Robot Framework
Classifier: Framework :: Robot Framework :: Library
Classifier: Topic :: Software Development :: Testing
Classifier: Topic :: Software Development :: Quality Assurance
Requires-Python: <3.15,>=3.9
License-File: LICENSE
Requires-Dist: robotframework>=7.0
Requires-Dist: robotframework-appiumlibrary<4.0.0,>=2.0.0
Requires-Dist: Appium-Python-Client<6.0.0,>=3.1.0
Requires-Dist: selenium<5.0.0,>=4.14.0
Requires-Dist: kitchen>=1.2.6
Requires-Dist: geopy>=2.4.1
Requires-Dist: urllib3>=2.0.7
Requires-Dist: certifi>=2024.2.2
Requires-Dist: idna>=3.7
Requires-Dist: six>=1.16.0
Requires-Dist: trio>=0.26.2
Requires-Dist: trio-websocket>=0.11.1
Requires-Dist: sniffio>=1.3.0
Requires-Dist: sortedcontainers>=2.4.0
Requires-Dist: attrs>=23.2.0
Requires-Dist: websocket-client>=1.8.0
Requires-Dist: wsproto>=1.2.0
Requires-Dist: PySocks>=1.7.1
Requires-Dist: outcome>=1.3.0
Requires-Dist: decorator>=5.1.1
Requires-Dist: docutils>=0.20.1
Requires-Dist: opencv-python-headless>=4.12.0.88
Requires-Dist: numpy>=2.0.0
Dynamic: license-file
